ci_version_tools/__init__.py
ci_version_tools/exceptions.py
ci_version_tools/git.py
ci_version_tools/helm.py
ci_version_tools/poetry.py
ci_version_tools/project.py
ci_version_tools/py.typed
ci_version_tools/util.py
ci_version_tools/version_env_vars.py
ci_version_tools-0.2.7.dist-info/LICENSE
ci_version_tools-0.2.7.dist-info/METADATA
ci_version_tools-0.2.7.dist-info/WHEEL
ci_version_tools-0.2.7.dist-info/entry_points.txt
ci_version_tools-0.2.7.dist-info/RECORD
