Metadata-Version: 2.3
Name: ci-version-tools
Version: 0.2.7
Summary: Versioning tools for CI
License: MIT
Author: Sergej Alikov
Author-email: sergej@alikov.com
Requires-Python: >=3.13,<4.0
Classifier: License :: OSI Approved :: MIT License
Classifier: Programming Language :: Python :: 3
Classifier: Programming Language :: Python :: 3.13
Requires-Dist: packaging (>=24.2,<25.0)
Requires-Dist: pyyaml (>=6.0.2,<7.0.0)
Requires-Dist: semver (>=3.0.4,<4.0.0)
